<level>
    <tilemap>
        <line>000,000,000,000,000,000,000,000,000,000,000,000,000,000,000,000</line>
        <line>000,000,000,000,000,000,000,000,000,000,000,000,000,000,000,000</line>
        <line>000,000,000,000,000,000,000,000,000,000,000,000,000,000,000,000</line>

        <line>000,000,000,000,000,000,000,000,000,000,000,000,000,000,000,000</line>
        <line>000,000,000,000,000,000,000,000,000,000,000,000,000,000,000,000</line>
        <line>000,907,901,901,901,901,901,901,901,901,901,901,901,901,904,000</line>
        <line>000,903,644,640,640,640,640,640,640,640,640,640,640,642,902,000</line>
        <line>907,911,645,641,641,641,641,641,641,641,641,641,641,643,908,000</line>
        <line>903,002,001,001,001,001,001,001,001,001,001,001,001,001,002,000</line>
        <line>903,002,001,001,001,001,001,001,001,001,001,001,001,001,002,000</line>
        <line>906,910,001,001,001,001,001,001,001,001,001,001,001,001,909,000</line>
        <line>000,906,900,900,900,900,900,900,900,900,900,900,900,900,905,000</line>
        <line>000,000,000,000,000,000,000,000,000,000,000,000,000,000,000,000</line>
        <line>000,000,000,000,000,000,000,000,000,000,000,000,000,000,000,000</line>
        <line>000,000,000,000,000,000,000,000,000,000,000,000,000,000,000,000</line>
        <line>000,000,000,000,000,000,000,000,000,000,000,000,000,000,000,000</line>
    </tilemap>

    <transitions>
        <transition><filename>scene_2/linsensouth.xml</filename><position>14,8</position><newPosition direction="down">7,6</newPosition></transition>
        <transition><filename>scene_2/linsensouth.xml</filename><position>14,9</position><newPosition direction="down">8,6</newPosition></transition>

        <transition><filename>scene_2/editsouthentrance.xml</filename><position>1,8</position><newPosition direction="down">7,6</newPosition></transition>
        <transition><filename>scene_2/editsouthentrance.xml</filename><position>1,9</position><newPosition direction="down">8,6</newPosition></transition>
    </transitions>

</level>